permuter/__init__.py
permuter/src/__init__.py
permuter/src/permuter.py
permuter-0.0.10.dist-info/LICENSE.txt
permuter-0.0.10.dist-info/METADATA
permuter-0.0.10.dist-info/WHEEL
permuter-0.0.10.dist-info/top_level.txt
permuter-0.0.10.dist-info/RECORD
